catwallpaper/__init__.py
catwallpaper-0.11.dist-info/LICENSE.txt
catwallpaper-0.11.dist-info/METADATA
catwallpaper-0.11.dist-info/WHEEL
catwallpaper-0.11.dist-info/entry_points.txt
catwallpaper-0.11.dist-info/top_level.txt
catwallpaper-0.11.dist-info/RECORD
