Metadata-Version: 2.1
Name: catwallpaper
Version: 0.11
Summary: Download and apply random cat wallpapers on every platform (windows, mac or even linux) automatically
Home-page: https://github.com/CyberSecByte/catwallpaper
Author: CyberSecByte
Author-email: cybersecbyte@gmail.com
Keywords: cat,catwallpaper,wallpaper,meow,cats
Classifier: License :: OSI Approved :: MIT License
Classifier: Topic :: System
Classifier: Programming Language :: Python
Classifier: Programming Language :: Python :: 3
License-File: LICENSE.txt
Requires-Dist: requests
